luminaut/__init__.py
luminaut/__main__.py
luminaut/core.py
luminaut/models.py
luminaut/report.py
luminaut/scanner.py
luminaut/tools/__init__.py
luminaut/tools/aws.py
luminaut/tools/gcp.py
luminaut/tools/gcp_audit_logs.py
luminaut/tools/whatweb.py
luminaut-0.13.2.dist-info/METADATA
luminaut-0.13.2.dist-info/WHEEL
luminaut-0.13.2.dist-info/entry_points.txt
luminaut-0.13.2.dist-info/licenses/LICENSE.md
luminaut-0.13.2.dist-info/RECORD
