Metadata-Version: 2.4
Name: luminaut
Version: 0.13.2
Summary: Casting light on shadow cloud deployments
Project-URL: Homepage, https://luminaut.org
Project-URL: Documentation, https://luminaut.org
Project-URL: Repository, https://github.com/luminaut-org/luminaut.git
Project-URL: Issues, https://github.com/luminaut-org/luminaut/issues
License-File: LICENSE.md
Classifier: Development Status :: 4 - Beta
Classifier: Environment :: Console
Classifier: Intended Audience :: Developers
Classifier: Intended Audience :: Information Technology
Classifier: Intended Audience :: System Administrators
Classifier: License :: OSI Approved :: MIT License
Classifier: Topic :: Security
Classifier: Topic :: Utilities
Requires-Python: >=3.11
Requires-Dist: boto3~=1.35.53
Requires-Dist: google-cloud-compute>=1.30.0
Requires-Dist: google-cloud-logging>=3.8.0
Requires-Dist: google-cloud-run>=0.10.18
Requires-Dist: orjson~=3.10.12
Requires-Dist: python3-nmap~=1.9.1
Requires-Dist: rich~=13.9.4
Requires-Dist: shodan~=1.31.0
Requires-Dist: tqdm>=4.67.1
